__init__.py
cli.py
github.py
tui.py
repostats-1.3.0.dist-info/licenses/LICENSE
repostats-1.3.0.dist-info/METADATA
repostats-1.3.0.dist-info/WHEEL
repostats-1.3.0.dist-info/entry_points.txt
repostats-1.3.0.dist-info/top_level.txt
repostats-1.3.0.dist-info/RECORD
