Metadata-Version: 2.4
Name: repostats
Version: 1.3.0
Summary: A CLI tool to fetch GitHub repository statistics
Author-email: Your Name <your.email@example.com>
License-Expression: MIT
Project-URL: Homepage, https://github.com/sahansera/repostats
Project-URL: Repository, https://github.com/sahansera/repostats
Project-URL: Issues, https://github.com/sahansera/repostats/issues
Keywords: github,statistics,cli,api
Classifier: Development Status :: 3 - Alpha
Classifier: Intended Audience :: Developers
Classifier: Programming Language :: Python :: 3
Classifier: Programming Language :: Python :: 3.8
Classifier: Programming Language :: Python :: 3.9
Classifier: Programming Language :: Python :: 3.10
Classifier: Programming Language :: Python :: 3.11
Classifier: Topic :: Software Development :: Build Tools
Requires-Python: >=3.8
License-File: LICENSE
Requires-Dist: requests>=2.28.2
Requires-Dist: click>=8.1.3
Requires-Dist: PyYAML>=6.0.1
Provides-Extra: tui
Requires-Dist: textual>=0.47.0; extra == "tui"
Provides-Extra: dev
Requires-Dist: pytest>=7.3.1; extra == "dev"
Requires-Dist: pytest-cov>=4.1.0; extra == "dev"
Requires-Dist: black>=23.3.0; extra == "dev"
Requires-Dist: isort>=5.12.0; extra == "dev"
Requires-Dist: mypy>=1.3.0; extra == "dev"
Requires-Dist: types-requests>=2.32.0; extra == "dev"
Requires-Dist: types-PyYAML>=6.0.0; extra == "dev"
Requires-Dist: textual>=0.47.0; extra == "dev"
Dynamic: license-file
